yaconf/__init__.py
yaconf/yaconf.py
yaconf-0.2.0.dist-info/AUTHORS.rst
yaconf-0.2.0.dist-info/LICENSE
yaconf-0.2.0.dist-info/METADATA
yaconf-0.2.0.dist-info/WHEEL
yaconf-0.2.0.dist-info/top_level.txt
yaconf-0.2.0.dist-info/RECORD
