Metadata-Version: 2.1
Name: yaconf
Version: 0.2.0
Summary: Yet another configuration library
Home-page: https://github.com/rasmuse/yaconf
Author: Rasmus Einarsson
Author-email: mr@rasmuseinarsson.se
License: MIT license
Keywords: yaconf
Platform: UNKNOWN
Classifier: Development Status :: 2 - Pre-Alpha
Classifier: Intended Audience :: Developers
Classifier: License :: OSI Approved :: MIT License
Classifier: Natural Language :: English
Classifier: Programming Language :: Python :: 3
Classifier: Programming Language :: Python :: 3.6
Classifier: Programming Language :: Python :: 3.7
